pbshm/ievisualiser/__init__.py
pbshm/ievisualiser/routes.py
pbshm/ievisualiser/static/css/builder.css
pbshm/ievisualiser/static/css/viewer.css
pbshm/ievisualiser/static/images/geometries.png
pbshm/ievisualiser/static/js/builder.js
pbshm/ievisualiser/static/js/colourHelper.js
pbshm/ievisualiser/static/js/geometryHelper.js
pbshm/ievisualiser/static/js/guiHelper.js
pbshm/ievisualiser/static/js/jsonHelper.js
pbshm/ievisualiser/static/js/loader.js
pbshm/ievisualiser/static/js/networkHelper.js
pbshm/ievisualiser/static/js/obliqueCylinder.js
pbshm/ievisualiser/static/js/translationHelper.js
pbshm/ievisualiser/static/js/trapezoid.js
pbshm/ievisualiser/static/js/viewer.js
pbshm/ievisualiser/templates/available-models.html
pbshm/ievisualiser/templates/build-model.html
pbshm/ievisualiser/templates/explore-model.html
pbshm_ie_visualiser-1.0.dist-info/licenses/LICENSE
pbshm_ie_visualiser-1.0.dist-info/METADATA
pbshm_ie_visualiser-1.0.dist-info/WHEEL
pbshm_ie_visualiser-1.0.dist-info/top_level.txt
pbshm_ie_visualiser-1.0.dist-info/RECORD
