Metadata-Version: 2.4
Name: pbshm-ie-visualiser
Version: 1.0
Summary: PBSHM Irreducible Element Model Visualiser
Author: Josie McCulloch
Author-email: Dan Brennan <d.s.brennan@sheffield.ac.uk>
License:                     GNU AFFERO GENERAL PUBLIC LICENSE
Project-URL: homepage, https://github.com/dynamics-research-group/pbshm-ie-model-builder
Classifier: License :: OSI Approved :: GNU Affero General Public License v3 or later (AGPLv3+)
Classifier: Programming Language :: Python :: 3
Classifier: Framework :: Flask
Requires-Python: >=3.8.10
License-File: LICENSE
Requires-Dist: pbshm-core==1.1.6
Dynamic: license-file
